odoo/addons/runbot_gitlab/README.rst
odoo/addons/runbot_gitlab/__init__.py
odoo/addons/runbot_gitlab/__manifest__.py
odoo/addons/runbot_gitlab/controllers/__init__.py
odoo/addons/runbot_gitlab/controllers/gitlab_ci_controller.py
odoo/addons/runbot_gitlab/models/__init__.py
odoo/addons/runbot_gitlab/models/runbot_branch.py
odoo/addons/runbot_gitlab/models/runbot_build.py
odoo/addons/runbot_gitlab/models/runbot_repo.py
odoo/addons/runbot_gitlab/static/description/icon.png
odoo/addons/runbot_gitlab/views/runbot_repo.xml
odoo11_addon_runbot_gitlab-11.0.1.0.0.dist-info/DESCRIPTION.rst
odoo11_addon_runbot_gitlab-11.0.1.0.0.dist-info/METADATA
odoo11_addon_runbot_gitlab-11.0.1.0.0.dist-info/RECORD
odoo11_addon_runbot_gitlab-11.0.1.0.0.dist-info/WHEEL
odoo11_addon_runbot_gitlab-11.0.1.0.0.dist-info/metadata.json
odoo11_addon_runbot_gitlab-11.0.1.0.0.dist-info/top_level.txt
